upt_fedora/__init__.py
upt_fedora/upt_fedora.py
upt_fedora/templates/base.spec
upt_fedora/templates/python.spec
upt_fedora/templates/ruby.spec
upt_fedora/tests/__init__.py
upt_fedora/tests/test_fedora_backend.py
upt_fedora/tests/test_fedora_package.py
upt_fedora/tests/test_python_package.py
upt_fedora/tests/test_ruby_package.py
upt_fedora-0.3.dist-info/LICENSE
upt_fedora-0.3.dist-info/METADATA
upt_fedora-0.3.dist-info/WHEEL
upt_fedora-0.3.dist-info/entry_points.txt
upt_fedora-0.3.dist-info/top_level.txt
upt_fedora-0.3.dist-info/RECORD
